LICENSE.txt
README.md
setup.cfg
setup.py
bicenv/__init__.py
bicenv/agv.py
bicenv/base_environment.py
bicenv/job.py
bicenv/job_queue.py
bicenv/parent_area.py
bicenv/path_finding.py
bicenv/pdnode.py
bicenv/request.py
bicenv/station.py
bicenv/stats.py
bicenv.egg-info/PKG-INFO
bicenv.egg-info/SOURCES.txt
bicenv.egg-info/dependency_links.txt
bicenv.egg-info/requires.txt
bicenv.egg-info/top_level.txt