Metadata-Version: 2.1
Name: bicenv
Version: 0.1
Summary: My BIC Environment
Author: Nitish Singh
Author-email: singhnitish.personal@gmail.com
License: MIT
Keywords: BIC,ENVIRONMENT
Classifier: Development Status :: 3 - Alpha
Classifier: Intended Audience :: Developers
Classifier: Topic :: Software Development :: Build Tools
Classifier: License :: OSI Approved :: MIT License
Classifier: Programming Language :: Python :: 3.6
License-File: LICENSE.txt
